setup.py
awsgi/__init__.py
awsgi/server.py
awsgi/websocket.py
awsgi.egg-info/PKG-INFO
awsgi.egg-info/SOURCES.txt
awsgi.egg-info/dependency_links.txt
awsgi.egg-info/requires.txt
awsgi.egg-info/top_level.txt
sample/__init__.py
sample/asyncapp.py
sample/uploader.py
sample/websocketapp.py
sample/wsgiapp.py
spec/__init__.py
spec/test_wsgi.py