Metadata-Version: 1.1
Name: awsgi
Version: 0.0.4
Summary: asynchronous wsgi server
Home-page: https://github.com/youngrok/awsgi
Author: Youngrok Pak
Author-email: pak.youngrok@gmail.com
License: UNKNOWN
Keywords: asyncio http server wsgi
Platform: UNKNOWN
Classifier: Development Status :: 3 - Alpha
Classifier: Topic :: Software Development :: Libraries
Classifier: License :: OSI Approved :: BSD License
